devices/BackgroundTick.py
devices/Pupil.py
devices/SMI.py
devices/__init__.py
devices/device.py
devices/eeg.py
devices/glasses.py
devices/glove.py
devices/leftglove.py
devices/pupil-tick.py
devices/rightglove.py
devices/suit.py
devices/watch.py
ethome/DataBase.py
ethome/__init__.py
ethome/ethome.py
ethome/makeDataLabels.py
tests/__init__.py
tests/test_add_methods.py
tests/test_script.py
utilities/BVH2BioMech.py
utilities/DCMTools.py
utilities/Multiple.py
utilities/__init__.py
utilities/deSwitch.py
utilities/h5transfer.py
utilities/libsmi.py
utilities/mvnx.py
utilities/npybvh.py
ethome-0.1.dist-info/LICENSE
ethome-0.1.dist-info/METADATA
ethome-0.1.dist-info/WHEEL
ethome-0.1.dist-info/top_level.txt
ethome-0.1.dist-info/RECORD
