Metadata-Version: 2.1
Name: ethome
Version: 0.1
Summary: ethome - a package for multimodal behavioural recordings
Home-page: https://github.com/alexharston/ethome
Author: Alex Harston
Author-email: alex@harston.io
License: MIT
Platform: UNKNOWN
Classifier: Programming Language :: Python :: 3
Classifier: License :: OSI Approved :: MIT License
Classifier: Operating System :: OS Independent
Requires-Python: >=3.6
Requires-Dist: scipy
Requires-Dist: numpy
Requires-Dist: sklearn
Requires-Dist: argparse
Requires-Dist: tqdm
Requires-Dist: h5py
Requires-Dist: pandas
Requires-Dist: mypy
Requires-Dist: bvhtoolbox
Requires-Dist: transforms3d
Requires-Dist: matplotlib
Requires-Dist: mne
Requires-Dist: mvnx
